vsptd.py
vsptd/__init__.py
vsptd/extra.py
vsptd/parse.py
vsptd/support.py
vsptd/vsptd.py
vsptd-2.0.0.dist-info/DESCRIPTION.rst
vsptd-2.0.0.dist-info/METADATA
vsptd-2.0.0.dist-info/RECORD
vsptd-2.0.0.dist-info/WHEEL
vsptd-2.0.0.dist-info/metadata.json
vsptd-2.0.0.dist-info/top_level.txt
