Metadata-Version: 2.0
Name: vsptd
Version: 2.0.0
Summary: vsptd — пакет библиотек для работы с ВСПТД в Python.
Home-page: https://github.com/become-iron/vsptd/
Author: UNKNOWN
Author-email: UNKNOWN
License: UNKNOWN
Keywords: vsptd,ВСПТД,ВСПТДЗ
Platform: UNKNOWN
Classifier: Operating System :: OS Independent
Classifier: Natural Language :: Russian
Classifier: Programming Language :: Python :: 3
Classifier: Programming Language :: Python :: 3.3
Classifier: Programming Language :: Python :: 3.4
Classifier: Programming Language :: Python :: 3.5
Classifier: Programming Language :: Python :: 3.6
